README
setup.py
glasnaegel/__init__.py
glasnaegel/decorators.py
glasnaegel.egg-info/PKG-INFO
glasnaegel.egg-info/SOURCES.txt
glasnaegel.egg-info/dependency_links.txt
glasnaegel.egg-info/top_level.txt
glasnaegel/bundles/__init__.py
glasnaegel/bundles/models.py
glasnaegel/bundles/admin/__init__.py
glasnaegel/bundles/auth/__init__.py
glasnaegel/bundles/auth/forms.py
glasnaegel/bundles/auth/models.py
glasnaegel/bundles/auth/views.py
glasnaegel/utils/__init__.py
glasnaegel/utils/appliance.py
glasnaegel/utils/webbish.py