Metadata-Version: 1.1
Name: glasnaegel
Version: 0.5.0
Summary: A set of shortcuts for the Glashammer web framework.
Home-page: http://bitbucket.org/neithere/glasnaegel/
Author: Andrey Mikhaylenko
Author-email: andy@neithere.net
License: GNU Lesser General Public License (LGPL), Version 3
Download-URL: http://bitbucket.org/neithere/glasnaegel/get/tip.zip
Keywords: Glashammer
Platform: UNKNOWN
Classifier: Development Status :: 4 - Beta
Classifier: Environment :: Web Environment
Classifier: Intended Audience :: Developers
Classifier: License :: OSI Approved :: GNU Library or Lesser General Public License (LGPL)
Classifier: Programming Language :: Python
Classifier: Topic :: Software Development :: Libraries :: Python Modules
Requires: python (>= 2.4)
Requires: glashammer (>= 0.3.0)
